basehash/__init__.py
basehash/primes.py
basehash/version.py
BaseHash-3.0.9.dist-info/LICENSE
BaseHash-3.0.9.dist-info/METADATA
BaseHash-3.0.9.dist-info/WHEEL
BaseHash-3.0.9.dist-info/top_level.txt
BaseHash-3.0.9.dist-info/RECORD
