Metadata-Version: 2.1
Name: BaseHash
Version: 3.0.9
Summary: Reversible obfuscated identifier hashes.
Home-page: http://bnlucas.github.io/python-basehash
Author: Nathan Lucas
Author-email: bnlucas@outlook.com
License: 
Keywords: base,encoding,hash,hashing,security
Platform: UNKNOWN
Classifier: Development Status :: 5 - Production/Stable
Classifier: Programming Language :: Python
Classifier: License :: OSI Approved :: Apache Software License
Classifier: Intended Audience :: Developers
Classifier: Operating System :: OS Independent
Classifier: Topic :: Scientific/Engineering :: Mathematics
Classifier: Topic :: Security
Classifier: Topic :: Software Development :: Libraries :: Python Modules
Classifier: Topic :: Utilities
License-File: LICENSE
Requires-Dist: six
